[
    {
        "name": "NL ЧЕРНЫЙ",
        "pathName": "ОПТ JFK\/КУПАЖИРОВАННЫЙ ЧАЙ",
        "href": "https:\/\/api.moysklad.ru\/api\/remap\/1.2\/entity\/productfolder\/0226dd93-ab27-11ef-0a80-07b6003b5e66"
    },
    {
        "name": "Стандарт ЧЕРНЫЙ",
        "pathName": "ОПТ JFK\/КУПАЖИРОВАННЫЙ ЧАЙ",
        "href": "https:\/\/api.moysklad.ru\/api\/remap\/1.2\/entity\/productfolder\/02d60755-ab26-11ef-0a80-10e7003a3c49"
    },
    {
        "name": "ВЬЕТНАМ",
        "pathName": "ОПТ JFK\/ТРАВЫ И ДОБАВКИ",
        "href": "https:\/\/api.moysklad.ru\/api\/remap\/1.2\/entity\/productfolder\/04816f5e-ab28-11ef-0a80-02cc003903f6"
    },
    {
        "name": "NL ЗЕЛЕНЫЙ",
        "pathName": "ОПТ JFK\/КУПАЖИРОВАННЫЙ ЧАЙ",
        "href": "https:\/\/api.moysklad.ru\/api\/remap\/1.2\/entity\/productfolder\/0b873fb7-ab27-11ef-0a80-01f2003991be"
    },
    {
        "name": "ИСПАНИЯ",
        "pathName": "ОПТ JFK\/ТРАВЫ И ДОБАВКИ",
        "href": "https:\/\/api.moysklad.ru\/api\/remap\/1.2\/entity\/productfolder\/0e53bce4-ab28-11ef-0a80-0e33003c1f8d"
    },
    {
        "name": "Стандарт ЗЕЛЕНЫЙ",
        "pathName": "ОПТ JFK\/КУПАЖИРОВАННЫЙ ЧАЙ",
        "href": "https:\/\/api.moysklad.ru\/api\/remap\/1.2\/entity\/productfolder\/10592633-ab26-11ef-0a80-11b5003afdc9"
    },
    {
        "name": "Премиум ЧЕРНЫЙ ИНДИЯ",
        "pathName": "ОПТ JFK\/КУПАЖИРОВАННЫЙ ЧАЙ",
        "href": "https:\/\/api.moysklad.ru\/api\/remap\/1.2\/entity\/productfolder\/184a96eb-ab1e-11ef-0a80-0d8900387431"
    },
    {
        "name": "ЮЖНАЯ АФРИКА",
        "pathName": "ОПТ JFK\/ТРАВЫ И ДОБАВКИ",
        "href": "https:\/\/api.moysklad.ru\/api\/remap\/1.2\/entity\/productfolder\/19164ed8-ab28-11ef-0a80-0811003aae30"
    },
    {
        "name": "Стандарт ЧЕРНЫЙ и ЗЕЛЕНЫЙ",
        "pathName": "ОПТ JFK\/КУПАЖИРОВАННЫЙ ЧАЙ",
        "href": "https:\/\/api.moysklad.ru\/api\/remap\/1.2\/entity\/productfolder\/1c8f166a-ab26-11ef-0a80-0811003a3582"
    },
    {
        "name": "Производство",
        "pathName": "",
        "href": "https:\/\/api.moysklad.ru\/api\/remap\/1.2\/entity\/productfolder\/233a1e76-ab16-11ef-0a80-11b50036edc8"
    },
    {
        "name": "Товары интернет-магазинов",
        "pathName": "",
        "href": "https:\/\/api.moysklad.ru\/api\/remap\/1.2\/entity\/productfolder\/24a079ad-a4a2-11ee-0a80-064d000a0345"
    },
    {
        "name": "jfkrus.ru",
        "pathName": "Товары интернет-магазинов",
        "href": "https:\/\/api.moysklad.ru\/api\/remap\/1.2\/entity\/productfolder\/24a13476-a4a2-11ee-0a80-064d000a0346"
    },
    {
        "name": "Стандарт ГРЕЧИШНЫЙ",
        "pathName": "ОПТ JFK\/КУПАЖИРОВАННЫЙ ЧАЙ",
        "href": "https:\/\/api.moysklad.ru\/api\/remap\/1.2\/entity\/productfolder\/26f2dea7-ab26-11ef-0a80-11b5003b0233"
    },
    {
        "name": "ИНДИЯ",
        "pathName": "ОПТ JFK",
        "href": "https:\/\/api.moysklad.ru\/api\/remap\/1.2\/entity\/productfolder\/2ffbc7d9-ab27-11ef-0a80-163f003b1f60"
    },
    {
        "name": "КУПАЖИРОВАННЫЙ ЧАЙ",
        "pathName": "ОПТ JFK",
        "href": "https:\/\/api.moysklad.ru\/api\/remap\/1.2\/entity\/productfolder\/3c1d5c69-ab17-11ef-0a80-02cc0034f402"
    },
    {
        "name": "ЦЕЙЛОН",
        "pathName": "ОПТ JFK",
        "href": "https:\/\/api.moysklad.ru\/api\/remap\/1.2\/entity\/productfolder\/3d7a0ede-ab27-11ef-0a80-1a730039b32c"
    },
    {
        "name": "Травы ягоды чай",
        "pathName": "Производство",
        "href": "https:\/\/api.moysklad.ru\/api\/remap\/1.2\/entity\/productfolder\/41db3eef-6543-11e6-7a69-93a70007c80b"
    },
    {
        "name": "ВЬЕТНАМ",
        "pathName": "ОПТ JFK",
        "href": "https:\/\/api.moysklad.ru\/api\/remap\/1.2\/entity\/productfolder\/47d4b9c1-ab27-11ef-0a80-10e7003a89bc"
    },
    {
        "name": "КИТАЙ",
        "pathName": "ОПТ JFK",
        "href": "https:\/\/api.moysklad.ru\/api\/remap\/1.2\/entity\/productfolder\/54577756-ab27-11ef-0a80-0975003bdef1"
    },
    {
        "name": "Индивидуальные рецептуры",
        "pathName": "ОПТ JFK\/КУПАЖИРОВАННЫЙ ЧАЙ",
        "href": "https:\/\/api.moysklad.ru\/api\/remap\/1.2\/entity\/productfolder\/588b7d3e-bd23-11ef-0a80-17d7001df1de"
    },
    {
        "name": "ПАКИСТАН",
        "pathName": "ОПТ JFK\/ТРАВЫ И ДОБАВКИ",
        "href": "https:\/\/api.moysklad.ru\/api\/remap\/1.2\/entity\/productfolder\/594f3f9b-acb2-11ef-0a80-1a7300689e84"
    },
    {
        "name": "НИГЕРИЯ",
        "pathName": "ОПТ JFK\/ТРАВЫ И ДОБАВКИ",
        "href": "https:\/\/api.moysklad.ru\/api\/remap\/1.2\/entity\/productfolder\/595d7d5d-ab28-11ef-0a80-11b5003b862e"
    },
    {
        "name": "Белый чай",
        "pathName": "ОПТ JFK\/КИТАЙ",
        "href": "https:\/\/api.moysklad.ru\/api\/remap\/1.2\/entity\/productfolder\/631cb8a7-ab27-11ef-0a80-163f003b2e94"
    },
    {
        "name": "ТАДЖИКИСТАН",
        "pathName": "ОПТ JFK\/ТРАВЫ И ДОБАВКИ",
        "href": "https:\/\/api.moysklad.ru\/api\/remap\/1.2\/entity\/productfolder\/63e14e51-ab28-11ef-0a80-10e7003ad2c7"
    },
    {
        "name": "Стандарт КАРКАДЕ",
        "pathName": "ОПТ JFK\/КУПАЖИРОВАННЫЙ ЧАЙ",
        "href": "https:\/\/api.moysklad.ru\/api\/remap\/1.2\/entity\/productfolder\/66c03d60-ab26-11ef-0a80-140b003a95ef"
    },
    {
        "name": "УЗБЕКИСТАН",
        "pathName": "ОПТ JFK\/ТРАВЫ И ДОБАВКИ",
        "href": "https:\/\/api.moysklad.ru\/api\/remap\/1.2\/entity\/productfolder\/6eb21d34-ab28-11ef-0a80-0811003ac0f2"
    },
    {
        "name": "Зеленый чай",
        "pathName": "ОПТ JFK\/КИТАЙ",
        "href": "https:\/\/api.moysklad.ru\/api\/remap\/1.2\/entity\/productfolder\/71a9ba6e-ab27-11ef-0a80-0e33003bffbe"
    },
    {
        "name": "Премиум ЗЕЛЕНЫЙ",
        "pathName": "ОПТ JFK\/КУПАЖИРОВАННЫЙ ЧАЙ",
        "href": "https:\/\/api.moysklad.ru\/api\/remap\/1.2\/entity\/productfolder\/73a73676-ab25-11ef-0a80-0c10003ae219"
    },
    {
        "name": "Стандарт АНЧАН",
        "pathName": "ОПТ JFK\/КУПАЖИРОВАННЫЙ ЧАЙ",
        "href": "https:\/\/api.moysklad.ru\/api\/remap\/1.2\/entity\/productfolder\/752c32f2-ab26-11ef-0a80-0429003a2535"
    },
    {
        "name": "Пряности",
        "pathName": "ОПТ JFK\/ПРИПРАВЫ",
        "href": "https:\/\/api.moysklad.ru\/api\/remap\/1.2\/entity\/productfolder\/7b5393c9-bddd-11ef-0a80-15660000488e"
    },
    {
        "name": "Связанный чай",
        "pathName": "ОПТ JFK\/КИТАЙ",
        "href": "https:\/\/api.moysklad.ru\/api\/remap\/1.2\/entity\/productfolder\/800cd0af-ab27-11ef-0a80-10e7003a9268"
    },
    {
        "name": "РОССИЯ",
        "pathName": "ОПТ JFK\/ТРАВЫ И ДОБАВКИ",
        "href": "https:\/\/api.moysklad.ru\/api\/remap\/1.2\/entity\/productfolder\/806948ce-ab28-11ef-0a80-02cc0039201b"
    },
    {
        "name": "ОПТ JFK",
        "pathName": "",
        "href": "https:\/\/api.moysklad.ru\/api\/remap\/1.2\/entity\/productfolder\/80b4500a-ab15-11ef-0a80-0c1000369750"
    },
    {
        "name": "ПРИПРАВЫ",
        "pathName": "ОПТ JFK",
        "href": "https:\/\/api.moysklad.ru\/api\/remap\/1.2\/entity\/productfolder\/89157457-ab28-11ef-0a80-140b003b20f7"
    },
    {
        "name": "Жасминовый чай",
        "pathName": "ОПТ JFK\/КИТАЙ",
        "href": "https:\/\/api.moysklad.ru\/api\/remap\/1.2\/entity\/productfolder\/8a81d53e-ab27-11ef-0a80-0d89003ab65f"
    },
    {
        "name": "Оборудование и общие закупки",
        "pathName": "Производство",
        "href": "https:\/\/api.moysklad.ru\/api\/remap\/1.2\/entity\/productfolder\/8ce498df-75b9-11e6-7a31-d0fd000c7652"
    },
    {
        "name": "Премиум КАРКАДЕ",
        "pathName": "ОПТ JFK\/КУПАЖИРОВАННЫЙ ЧАЙ",
        "href": "https:\/\/api.moysklad.ru\/api\/remap\/1.2\/entity\/productfolder\/8f43a2fd-ab25-11ef-0a80-10e7003a1fda"
    },
    {
        "name": "Эконом",
        "pathName": "ОПТ JFK\/ПРИПРАВЫ",
        "href": "https:\/\/api.moysklad.ru\/api\/remap\/1.2\/entity\/productfolder\/909dd384-ab28-11ef-0a80-0811003ace0f"
    },
    {
        "name": "Стандарт DETOX",
        "pathName": "ОПТ JFK\/КУПАЖИРОВАННЫЙ ЧАЙ",
        "href": "https:\/\/api.moysklad.ru\/api\/remap\/1.2\/entity\/productfolder\/9200c35a-ab26-11ef-0a80-0975003bac79"
    },
    {
        "name": "Чаеподобные напитки",
        "pathName": "ОПТ JFK\/КИТАЙ",
        "href": "https:\/\/api.moysklad.ru\/api\/remap\/1.2\/entity\/productfolder\/96410270-ab27-11ef-0a80-02cc0038e8fc"
    },
    {
        "name": "Премиум",
        "pathName": "ОПТ JFK\/ПРИПРАВЫ",
        "href": "https:\/\/api.moysklad.ru\/api\/remap\/1.2\/entity\/productfolder\/98ed6191-ab28-11ef-0a80-11b5003b963a"
    },
    {
        "name": "ИНДИЯ",
        "pathName": "ОПТ JFK\/ТРАВЫ И ДОБАВКИ",
        "href": "https:\/\/api.moysklad.ru\/api\/remap\/1.2\/entity\/productfolder\/9e14d529-acb3-11ef-0a80-1a730068f2de"
    },
    {
        "name": "Улун",
        "pathName": "ОПТ JFK\/КИТАЙ",
        "href": "https:\/\/api.moysklad.ru\/api\/remap\/1.2\/entity\/productfolder\/a4643f79-ab27-11ef-0a80-02cc0038eba0"
    },
    {
        "name": "Маркетплейсы",
        "pathName": "",
        "href": "https:\/\/api.moysklad.ru\/api\/remap\/1.2\/entity\/productfolder\/a4a9a4f5-e98b-11ed-0a80-110800506d64"
    },
    {
        "name": "НАСТОЙКИ",
        "pathName": "ОПТ JFK",
        "href": "https:\/\/api.moysklad.ru\/api\/remap\/1.2\/entity\/productfolder\/ac1ee107-ab28-11ef-0a80-0c10003baeda"
    },
    {
        "name": "Пуэр листовой",
        "pathName": "ОПТ JFK\/КИТАЙ",
        "href": "https:\/\/api.moysklad.ru\/api\/remap\/1.2\/entity\/productfolder\/ad6a3e92-ab27-11ef-0a80-11b5003b64e7"
    },
    {
        "name": "Пуэр прессованный",
        "pathName": "ОПТ JFK\/КИТАЙ",
        "href": "https:\/\/api.moysklad.ru\/api\/remap\/1.2\/entity\/productfolder\/b7d2afc3-ab27-11ef-0a80-0c10003b702c"
    },
    {
        "name": "Стандарт ДА ХУН ПАО",
        "pathName": "ОПТ JFK\/КУПАЖИРОВАННЫЙ ЧАЙ",
        "href": "https:\/\/api.moysklad.ru\/api\/remap\/1.2\/entity\/productfolder\/b993cf4b-ab26-11ef-0a80-0429003a3357"
    },
    {
        "name": "Ароматизаторы",
        "pathName": "Производство",
        "href": "https:\/\/api.moysklad.ru\/api\/remap\/1.2\/entity\/productfolder\/be728529-6542-11e6-7a69-93a70007b155"
    },
    {
        "name": "Красный чай",
        "pathName": "ОПТ JFK\/КИТАЙ",
        "href": "https:\/\/api.moysklad.ru\/api\/remap\/1.2\/entity\/productfolder\/c49d3773-ab27-11ef-0a80-0975003bef44"
    },
    {
        "name": "Стандарт ТРАВЯНОЙ",
        "pathName": "ОПТ JFK\/КУПАЖИРОВАННЫЙ ЧАЙ",
        "href": "https:\/\/api.moysklad.ru\/api\/remap\/1.2\/entity\/productfolder\/c544d548-ab26-11ef-0a80-11b5003b2b27"
    },
    {
        "name": "Стандарт УЛУН",
        "pathName": "ОПТ JFK\/КУПАЖИРОВАННЫЙ ЧАЙ",
        "href": "https:\/\/api.moysklad.ru\/api\/remap\/1.2\/entity\/productfolder\/d0960a76-ab26-11ef-0a80-1a7300399626"
    },
    {
        "name": "КЕНИЯ",
        "pathName": "ОПТ JFK",
        "href": "https:\/\/api.moysklad.ru\/api\/remap\/1.2\/entity\/productfolder\/d114121f-ab27-11ef-0a80-0811003a9c4c"
    },
    {
        "name": "Стандарт ПУЭР",
        "pathName": "ОПТ JFK\/КУПАЖИРОВАННЫЙ ЧАЙ",
        "href": "https:\/\/api.moysklad.ru\/api\/remap\/1.2\/entity\/productfolder\/dbb6089f-ab26-11ef-0a80-02cc0038bd79"
    },
    {
        "name": "ТРАВЫ И ДОБАВКИ",
        "pathName": "ОПТ JFK",
        "href": "https:\/\/api.moysklad.ru\/api\/remap\/1.2\/entity\/productfolder\/de1934ee-ab27-11ef-0a80-07b6003b8bef"
    },
    {
        "name": "Стандарт РОЙБОС",
        "pathName": "ОПТ JFK\/КУПАЖИРОВАННЫЙ ЧАЙ",
        "href": "https:\/\/api.moysklad.ru\/api\/remap\/1.2\/entity\/productfolder\/e4eb6689-ab26-11ef-0a80-10e7003a717f"
    },
    {
        "name": "Премиум ЧЕРНЫЙ ЦЕЙЛОН",
        "pathName": "ОПТ JFK\/КУПАЖИРОВАННЫЙ ЧАЙ",
        "href": "https:\/\/api.moysklad.ru\/api\/remap\/1.2\/entity\/productfolder\/e58ba19d-ab1e-11ef-0a80-02cc0036d6bc"
    },
    {
        "name": "Стандарт МАТЕ",
        "pathName": "ОПТ JFK\/КУПАЖИРОВАННЫЙ ЧАЙ",
        "href": "https:\/\/api.moysklad.ru\/api\/remap\/1.2\/entity\/productfolder\/edf4fd9f-ab26-11ef-0a80-07b6003b5b5f"
    },
    {
        "name": "ЕГИПЕТ",
        "pathName": "ОПТ JFK\/ТРАВЫ И ДОБАВКИ",
        "href": "https:\/\/api.moysklad.ru\/api\/remap\/1.2\/entity\/productfolder\/ee185592-ab27-11ef-0a80-0429003aa5d2"
    },
    {
        "name": "Премиум ЧЕРНЫЙ и ЗЕЛЕНЫЙ",
        "pathName": "ОПТ JFK\/КУПАЖИРОВАННЫЙ ЧАЙ",
        "href": "https:\/\/api.moysklad.ru\/api\/remap\/1.2\/entity\/productfolder\/f3d6af16-ab25-11ef-0a80-0d89003a5d75"
    },
    {
        "name": "Стандарт ИВАН-ЧАЙ",
        "pathName": "ОПТ JFK\/КУПАЖИРОВАННЫЙ ЧАЙ",
        "href": "https:\/\/api.moysklad.ru\/api\/remap\/1.2\/entity\/productfolder\/f5ef317e-ab26-11ef-0a80-1a730039a1fc"
    },
    {
        "name": "КИТАЙ",
        "pathName": "ОПТ JFK\/ТРАВЫ И ДОБАВКИ",
        "href": "https:\/\/api.moysklad.ru\/api\/remap\/1.2\/entity\/productfolder\/f783610f-ab27-11ef-0a80-07b6003b920f"
    }
]